intensity_normalization/__init__.py
intensity_normalization/cli.py
intensity_normalization/py.typed
intensity_normalization/adapters/__init__.py
intensity_normalization/adapters/images.py
intensity_normalization/adapters/io.py
intensity_normalization/domain/__init__.py
intensity_normalization/domain/exceptions.py
intensity_normalization/domain/models.py
intensity_normalization/domain/protocols.py
intensity_normalization/normalizers/__init__.py
intensity_normalization/normalizers/individual/__init__.py
intensity_normalization/normalizers/individual/fcm.py
intensity_normalization/normalizers/individual/kde.py
intensity_normalization/normalizers/individual/whitestripe.py
intensity_normalization/normalizers/individual/zscore.py
intensity_normalization/normalizers/population/__init__.py
intensity_normalization/normalizers/population/lsq.py
intensity_normalization/normalizers/population/nyul.py
intensity_normalization/services/__init__.py
intensity_normalization/services/normalization.py
intensity_normalization/services/validation.py
intensity_normalization-3.0.0.dist-info/METADATA
intensity_normalization-3.0.0.dist-info/WHEEL
intensity_normalization-3.0.0.dist-info/entry_points.txt
intensity_normalization-3.0.0.dist-info/licenses/LICENSE
intensity_normalization-3.0.0.dist-info/RECORD
