Metadata-Version: 2.4
Name: intensity-normalization
Version: 3.0.0
Summary: Normalize intensities of MR image modalities
Project-URL: Documentation, https://intensity-normalization.readthedocs.io/
Project-URL: Homepage, https://github.com/jcreinhold/intensity-normalization
Project-URL: Issues, https://github.com/jcreinhold/intensity-normalization/issues
Project-URL: Repository, https://github.com/jcreinhold/intensity-normalization
Author: Jacob Reinhold
License: MIT License
License-File: LICENSE
Classifier: Development Status :: 5 - Production/Stable
Classifier: Intended Audience :: Healthcare Industry
Classifier: Intended Audience :: Science/Research
Classifier: License :: OSI Approved :: MIT License
Classifier: Programming Language :: Python :: 3
Classifier: Programming Language :: Python :: 3.11
Classifier: Programming Language :: Python :: 3.12
Classifier: Programming Language :: Python :: 3.13
Classifier: Topic :: Scientific/Engineering :: Image Processing
Classifier: Topic :: Scientific/Engineering :: Medical Science Apps.
Requires-Python: >=3.11
Requires-Dist: nibabel>=5.0.0
Requires-Dist: numpy>=1.24.0
Requires-Dist: scikit-fuzzy>=0.4.2
Requires-Dist: scipy>=1.10.0
Provides-Extra: dev
Requires-Dist: mypy>=1.0.0; extra == 'dev'
Requires-Dist: pytest-cov>=4.0.0; extra == 'dev'
Requires-Dist: pytest>=7.0.0; extra == 'dev'
Requires-Dist: ruff>=0.1.0; extra == 'dev'
